docsbot/__init__.py
docsbot/base.py
docsbot/cli.py
docsbot/config.py
docsbot/version.py
tests/__init__.py
tests/test_base.py
docsbot-0.1.25.dist-info/METADATA
docsbot-0.1.25.dist-info/WHEEL
docsbot-0.1.25.dist-info/entry_points.txt
docsbot-0.1.25.dist-info/top_level.txt
docsbot-0.1.25.dist-info/RECORD
