Metadata-Version: 2.1
Name: docsbot
Version: 0.1.25
Summary: A simple chat bot for querying information from your local private documents.
Home-page: https://github.com/DataMini/docsbot
Author: lele
Requires-Dist: chromadb ==0.4.5
Requires-Dist: prettytable
Requires-Dist: langchain >=0.0.253
Requires-Dist: qdrant-client
Requires-Dist: unstructured
Requires-Dist: pytesseract
Requires-Dist: openai
Requires-Dist: python-docx
Requires-Dist: nltk
Requires-Dist: tiktoken
